pyrtkgps/__init__.py
pyrtkgps/ublox/__init__.py
pyrtkgps/ublox/StreamMuxDemux/StreamMuxDemux.py
pyrtkgps/ublox/StreamMuxDemux/StreamMuxDemuxError.py
pyrtkgps/ublox/StreamMuxDemux/UBloxQueue.py
pyrtkgps/ublox/StreamMuxDemux/UBloxReaderDEMUX.py
pyrtkgps/ublox/StreamMuxDemux/UBloxStream.py
pyrtkgps/ublox/StreamMuxDemux/UBloxWriterMUX.py
pyrtkgps/ublox/StreamMuxDemux/__init__.py
pyrtkgps/ublox/UBXSerializer/UBXSerializer.py
pyrtkgps/ublox/UBXSerializer/__init__.py
pyrtkgps/ublox/UBXSerializer/schema.py
pyrtkgps-0.0.11.dist-info/LICENSE
pyrtkgps-0.0.11.dist-info/METADATA
pyrtkgps-0.0.11.dist-info/WHEEL
pyrtkgps-0.0.11.dist-info/top_level.txt
pyrtkgps-0.0.11.dist-info/RECORD
